cmyt/__init__.py
cmyt/_utils.py
cmyt/cm.py
cmyt/py.typed
cmyt/colormaps/__init__.py
cmyt/colormaps/algae.py
cmyt/colormaps/apricity.py
cmyt/colormaps/arbre.py
cmyt/colormaps/dusk.py
cmyt/colormaps/kelp.py
cmyt/colormaps/octarine.py
cmyt/colormaps/pastel.py
cmyt/colormaps/pixel_blue.py
cmyt/colormaps/pixel_green.py
cmyt/colormaps/pixel_red.py
cmyt/colormaps/xray.py
cmyt-2.0.1.dist-info/METADATA
cmyt-2.0.1.dist-info/WHEEL
cmyt-2.0.1.dist-info/licenses/LICENSE
cmyt-2.0.1.dist-info/RECORD
