Metadata-Version: 2.3
Name: cmyt
Version: 2.0.1
Summary: A collection of Matplotlib colormaps from the yt project
Project-URL: Homepage, https://yt-project.org/
Project-URL: Source, https://github.com/yt-project/cmyt/
Project-URL: Tracker, https://github.com/yt-project/cmyt/issues
Author-email: The yt project <yt-dev@python.org>
License: BSD 3-Clause
Keywords: visualization
Classifier: Development Status :: 5 - Production/Stable
Classifier: Framework :: Matplotlib
Classifier: Intended Audience :: Science/Research
Classifier: License :: OSI Approved :: BSD License
Classifier: Operating System :: MacOS :: MacOS X
Classifier: Operating System :: POSIX :: AIX
Classifier: Operating System :: POSIX :: Linux
Classifier: Programming Language :: Python :: 3
Classifier: Topic :: Scientific/Engineering :: Visualization
Classifier: Typing :: Typed
Requires-Python: >=3.10
Requires-Dist: matplotlib>=3.8.0
Requires-Dist: numpy<3,>=1.26.0
